fsblueprint/__main__.py
fsblueprint/cli.py
fsblueprint/core/__init__.py
fsblueprint/core/blueprint.py
fsblueprint/core/ignore_patterns.py
fsblueprint/core/scaffold.py
fsblueprint/core/utils.py
fsblueprint-0.3.1.dist-info/METADATA
fsblueprint-0.3.1.dist-info/WHEEL
fsblueprint-0.3.1.dist-info/entry_points.txt
fsblueprint-0.3.1.dist-info/licenses/LICENSE
fsblueprint-0.3.1.dist-info/RECORD
