Metadata-Version: 2.4
Name: fsblueprint
Version: 0.3.1
Summary: Bidirectional YAML ↔ Directory Structure Tool
Project-URL: Homepage, https://github.com/zuxi-oss/fsblueprint
Project-URL: Repository, https://github.com/zuxi-oss/fsblueprint
Author-email: Zuki <sannimarzuk@gmail.com>
License: MIT
License-File: LICENSE
Keywords: directory,filesystem,scaffold,structure,yaml
Classifier: Development Status :: 4 - Beta
Classifier: Intended Audience :: Developers
Classifier: License :: OSI Approved :: MIT License
Classifier: Programming Language :: Python :: 3
Classifier: Programming Language :: Python :: 3.8
Classifier: Programming Language :: Python :: 3.9
Classifier: Programming Language :: Python :: 3.10
Classifier: Programming Language :: Python :: 3.11
Classifier: Programming Language :: Python :: 3.12
Requires-Python: >=3.8
Requires-Dist: pyyaml>=6.0.2
